[{"id":1,"first_name":"Letta","last_name":"MacGille","email":"lmacgille0@cornell.edu","gender":"Female"},
{"id":2,"first_name":"Vanessa","last_name":"Dinning","email":"vdinning1@epa.gov","gender":"Female"},
{"id":3,"first_name":"Suzie","last_name":"Ethersey","email":"sethersey2@mozilla.org","gender":"Female"},
{"id":4,"first_name":"Will","last_name":"Aymeric","email":"waymeric3@oaic.gov.au","gender":"Male"},
{"id":5,"first_name":"Chas","last_name":"Piff","email":"cpiff4@csmonitor.com","gender":"Male"},
{"id":6,"first_name":"Samaria","last_name":"Swadon","email":"sswadon5@whitehouse.gov","gender":"Female"},
{"id":7,"first_name":"Matthias","last_name":"Gilardone","email":"mgilardone6@nymag.com","gender":"Male"},
{"id":8,"first_name":"Adah","last_name":"Drogan","email":"adrogan7@ucla.edu","gender":"Female"},
{"id":9,"first_name":"Johnna","last_name":"Cartmale","email":"jcartmale8@zdnet.com","gender":"Female"},
{"id":10,"first_name":"Ingeberg","last_name":"Wallbrook","email":"iwallbrook9@usatoday.com","gender":"Female"},
{"id":11,"first_name":"Reed","last_name":"Kempton","email":"rkemptona@nytimes.com","gender":"Male"},
{"id":12,"first_name":"Margarita","last_name":"Stevens","email":"mstevensb@github.io","gender":"Female"},
{"id":13,"first_name":"Barrie","last_name":"Blackburn","email":"bblackburnc@dedecms.com","gender":"Female"},
{"id":14,"first_name":"Chandler","last_name":"Kirkham","email":"ckirkhamd@opensource.org","gender":"Male"},
{"id":15,"first_name":"Reece","last_name":"Blueman","email":"rbluemane@flickr.com","gender":"Male"},
{"id":16,"first_name":"Tami","last_name":"Jensen","email":"tjensenf@diigo.com","gender":"Female"},
{"id":17,"first_name":"Carilyn","last_name":"Schruur","email":"cschruurg@networksolutions.com","gender":"Female"},
{"id":18,"first_name":"Abagail","last_name":"Ainger","email":"aaingerh@google.cn","gender":"Female"},
{"id":19,"first_name":"Everard","last_name":"Duncombe","email":"eduncombei@blogs.com","gender":"Male"},
{"id":20,"first_name":"Brig","last_name":"Wilshere","email":"bwilsherej@naver.com","gender":"Male"},
{"id":21,"first_name":"Isabeau","last_name":"Eite","email":"ieitek@so-net.ne.jp","gender":"Female"},
{"id":22,"first_name":"Ado","last_name":"McGrady","email":"amcgradyl@mayoclinic.com","gender":"Male"},
{"id":23,"first_name":"Tedie","last_name":"Hasker","email":"thaskerm@wsj.com","gender":"Male"},
{"id":24,"first_name":"Jarad","last_name":"Le febre","email":"jlefebren@dyndns.org","gender":"Male"},
{"id":25,"first_name":"Barbe","last_name":"Daniell","email":"bdaniello@wisc.edu","gender":"Female"},
{"id":26,"first_name":"Elayne","last_name":"Krolak","email":"ekrolakp@epa.gov","gender":"Female"},
{"id":27,"first_name":"Levin","last_name":"Wharin","email":"lwharinq@businessweek.com","gender":"Male"},
{"id":28,"first_name":"Imelda","last_name":"Bendle","email":"ibendler@sakura.ne.jp","gender":"Female"},
{"id":29,"first_name":"Clementia","last_name":"Eddies","email":"ceddiess@acquirethisname.com","gender":"Female"},
{"id":30,"first_name":"Decca","last_name":"Proske","email":"dprosket@ox.ac.uk","gender":"Male"},
{"id":31,"first_name":"Greta","last_name":"Rosone","email":"grosoneu@weather.com","gender":"Female"},
{"id":32,"first_name":"Abraham","last_name":"Etock","email":"aetockv@google.com.au","gender":"Male"},
{"id":33,"first_name":"Ora","last_name":"Booy","email":"obooyw@hatena.ne.jp","gender":"Female"},
{"id":34,"first_name":"Berti","last_name":"Durrell","email":"bdurrellx@lulu.com","gender":"Female"},
{"id":35,"first_name":"Bale","last_name":"Yeeles","email":"byeelesy@dailymotion.com","gender":"Male"},
{"id":36,"first_name":"Tania","last_name":"Vasic","email":"tvasicz@tiny.cc","gender":"Female"},
{"id":37,"first_name":"Artemas","last_name":"Le land","email":"aleland10@bizjournals.com","gender":"Male"},
{"id":38,"first_name":"Edwin","last_name":"Eagling","email":"eeagling11@irs.gov","gender":"Male"},
{"id":39,"first_name":"Janene","last_name":"Benet","email":"jbenet12@booking.com","gender":"Female"},
{"id":40,"first_name":"Delphinia","last_name":"Kegley","email":"dkegley13@myspace.com","gender":"Female"},
{"id":41,"first_name":"Axe","last_name":"Silson","email":"asilson14@wikimedia.org","gender":"Male"},
{"id":42,"first_name":"Flo","last_name":"Etherson","email":"fetherson15@a8.net","gender":"Female"},
{"id":43,"first_name":"Jeth","last_name":"Royle","email":"jroyle16@mtv.com","gender":"Male"},
{"id":44,"first_name":"Karlens","last_name":"Habbes","email":"khabbes17@nytimes.com","gender":"Male"},
{"id":45,"first_name":"Freddie","last_name":"Fulham","email":"ffulham18@ucsd.edu","gender":"Female"},
{"id":46,"first_name":"Gustaf","last_name":"Dossantos","email":"gdossantos19@studiopress.com","gender":"Male"},
{"id":47,"first_name":"Lewes","last_name":"Dowtry","email":"ldowtry1a@japanpost.jp","gender":"Male"},
{"id":48,"first_name":"Allison","last_name":"Geale","email":"ageale1b@army.mil","gender":"Female"},
{"id":49,"first_name":"Leslie","last_name":"Moneypenny","email":"lmoneypenny1c@imdb.com","gender":"Female"},
{"id":50,"first_name":"Maighdiln","last_name":"Hatterslay","email":"mhatterslay1d@dell.com","gender":"Female"},
{"id":51,"first_name":"Haleigh","last_name":"Ryding","email":"hryding1e@ed.gov","gender":"Female"},
{"id":52,"first_name":"Sheila-kathryn","last_name":"Thexton","email":"sthexton1f@biglobe.ne.jp","gender":"Female"},
{"id":53,"first_name":"Becca","last_name":"Syvret","email":"bsyvret1g@taobao.com","gender":"Female"},
{"id":54,"first_name":"Evonne","last_name":"Dreinan","email":"edreinan1h@moonfruit.com","gender":"Female"},
{"id":55,"first_name":"Allegra","last_name":"Bridgewood","email":"abridgewood1i@gnu.org","gender":"Female"},
{"id":56,"first_name":"Evin","last_name":"Murrells","email":"emurrells1j@so-net.ne.jp","gender":"Male"},
{"id":57,"first_name":"Rhianna","last_name":"Tingle","email":"rtingle1k@delicious.com","gender":"Female"},
{"id":58,"first_name":"Laurence","last_name":"Esch","email":"lesch1l@usda.gov","gender":"Male"},
{"id":59,"first_name":"Tonye","last_name":"Toffoletto","email":"ttoffoletto1m@slate.com","gender":"Female"},
{"id":60,"first_name":"Ricard","last_name":"Kunzel","email":"rkunzel1n@theglobeandmail.com","gender":"Male"},
{"id":61,"first_name":"Isidro","last_name":"Jecock","email":"ijecock1o@usa.gov","gender":"Male"},
{"id":62,"first_name":"Carlotta","last_name":"Harcus","email":"charcus1p@cornell.edu","gender":"Female"},
{"id":63,"first_name":"Bellanca","last_name":"Goreisr","email":"bgoreisr1q@shinystat.com","gender":"Female"},
{"id":64,"first_name":"Ganny","last_name":"Bligh","email":"gbligh1r@aol.com","gender":"Male"},
{"id":65,"first_name":"Adele","last_name":"McCusker","email":"amccusker1s@yellowpages.com","gender":"Female"},
{"id":66,"first_name":"Carolynn","last_name":"Bonavia","email":"cbonavia1t@java.com","gender":"Female"},
{"id":67,"first_name":"Kristofor","last_name":"Reolfi","email":"kreolfi1u@umich.edu","gender":"Male"},
{"id":68,"first_name":"Sibyl","last_name":"Champneys","email":"schampneys1v@ifeng.com","gender":"Female"},
{"id":69,"first_name":"Drusie","last_name":"Delf","email":"ddelf1w@unc.edu","gender":"Female"},
{"id":70,"first_name":"Harrietta","last_name":"Duigenan","email":"hduigenan1x@123-reg.co.uk","gender":"Female"},
{"id":71,"first_name":"Lynnet","last_name":"Melchior","email":"lmelchior1y@unc.edu","gender":"Female"},
{"id":72,"first_name":"Kristy","last_name":"MacElharge","email":"kmacelharge1z@psu.edu","gender":"Female"},
{"id":73,"first_name":"Grange","last_name":"Calvert","email":"gcalvert20@networksolutions.com","gender":"Male"},
{"id":74,"first_name":"Kristyn","last_name":"Anmore","email":"kanmore21@yahoo.com","gender":"Female"},
{"id":75,"first_name":"Elia","last_name":"Hazle","email":"ehazle22@unc.edu","gender":"Male"},
{"id":76,"first_name":"Amabelle","last_name":"Bauldrey","email":"abauldrey23@latimes.com","gender":"Female"},
{"id":77,"first_name":"Jacquelyn","last_name":"Birks","email":"jbirks24@addthis.com","gender":"Female"},
{"id":78,"first_name":"Bridgette","last_name":"Danneil","email":"bdanneil25@loc.gov","gender":"Female"},
{"id":79,"first_name":"Sigismundo","last_name":"Rogers","email":"srogers26@berkeley.edu","gender":"Male"},
{"id":80,"first_name":"Stanton","last_name":"Strathe","email":"sstrathe27@ocn.ne.jp","gender":"Male"},
{"id":81,"first_name":"Humphrey","last_name":"Tolliday","email":"htolliday28@cbc.ca","gender":"Male"},
{"id":82,"first_name":"Manda","last_name":"Gomery","email":"mgomery29@princeton.edu","gender":"Female"},
{"id":83,"first_name":"Edna","last_name":"Palatini","email":"epalatini2a@java.com","gender":"Female"},
{"id":84,"first_name":"Berky","last_name":"Oneile","email":"boneile2b@etsy.com","gender":"Male"},
{"id":85,"first_name":"Bella","last_name":"Gother","email":"bgother2c@mapquest.com","gender":"Female"},
{"id":86,"first_name":"Kandy","last_name":"Pittendreigh","email":"kpittendreigh2d@telegraph.co.uk","gender":"Female"},
{"id":87,"first_name":"Isabelle","last_name":"Aldrich","email":"ialdrich2e@indiegogo.com","gender":"Female"},
{"id":88,"first_name":"Lauretta","last_name":"Dyter","email":"ldyter2f@vimeo.com","gender":"Female"},
{"id":89,"first_name":"Roslyn","last_name":"Killigrew","email":"rkilligrew2g@domainmarket.com","gender":"Female"},
{"id":90,"first_name":"Gipsy","last_name":"Crich","email":"gcrich2h@stumbleupon.com","gender":"Female"},
{"id":91,"first_name":"Adriana","last_name":"Ivankin","email":"aivankin2i@mozilla.com","gender":"Female"},
{"id":92,"first_name":"Orbadiah","last_name":"Englishby","email":"oenglishby2j@ezinearticles.com","gender":"Male"},
{"id":93,"first_name":"Elvis","last_name":"Roscam","email":"eroscam2k@flickr.com","gender":"Male"},
{"id":94,"first_name":"Abrahan","last_name":"Coldbreath","email":"acoldbreath2l@sogou.com","gender":"Male"},
{"id":95,"first_name":"Markos","last_name":"Linsey","email":"mlinsey2m@mac.com","gender":"Male"},
{"id":96,"first_name":"Spenser","last_name":"Clyne","email":"sclyne2n@furl.net","gender":"Male"},
{"id":97,"first_name":"Barrett","last_name":"Treasure","email":"btreasure2o@bigcartel.com","gender":"Male"},
{"id":98,"first_name":"Myrtia","last_name":"Alonso","email":"malonso2p@freewebs.com","gender":"Female"},
{"id":99,"first_name":"Kameko","last_name":"Battey","email":"kbattey2q@angelfire.com","gender":"Female"},
{"id":100,"first_name":"Adrien","last_name":"MacMurray","email":"amacmurray2r@squidoo.com","gender":"Male"}]